blockchain/__init__.py
blockchain/blockchain.py
tests/__init__.py
tests/test.py
tests/test_blockchain.py
simply_blockchain-0.1.0.dist-info/LICENSE
simply_blockchain-0.1.0.dist-info/METADATA
simply_blockchain-0.1.0.dist-info/WHEEL
simply_blockchain-0.1.0.dist-info/top_level.txt
simply_blockchain-0.1.0.dist-info/RECORD
